swiftannotate/__init__.py
swiftannotate/constants.py
swiftannotate/image/__init__.py
swiftannotate/image/base.py
swiftannotate/image/captioning.py
swiftannotate/image/classification.py
swiftannotate/image/object_detection.py
swiftannotate/image/segmentation.py
swiftannotate/image/utils.py
swiftannotate/text/__init__.py
swiftannotate/text/classification.py
swiftannotate/text/summarization.py
swiftannotate/text/text_generation.py
swiftannotate/video/__init__.py
swiftannotate/video/captioning.py
swiftannotate/video/segmentation.py
swiftannotate-0.1.0.dist-info/LICENSE
swiftannotate-0.1.0.dist-info/METADATA
swiftannotate-0.1.0.dist-info/WHEEL
swiftannotate-0.1.0.dist-info/RECORD
