Metadata-Version: 2.3
Name: swiftannotate
Version: 0.1.0
Summary: Auto annotation tool for Text, Images, and Videos.
License: Apache-2.0
Author: Yashowardhan
Author-email: yashowardhanshinde@gmail.com
Requires-Python: >=3.10
Classifier: License :: OSI Approved :: Apache Software License
Classifier: Programming Language :: Python :: 3
Classifier: Programming Language :: Python :: 3.10
Classifier: Programming Language :: Python :: 3.11
Classifier: Programming Language :: Python :: 3.12
Classifier: Programming Language :: Python :: 3.13
Requires-Dist: accelerate (==0.30.0)
Requires-Dist: google-generativeai (>=0.8.3,<0.9.0)
Requires-Dist: numpy (>=2.2.2,<3.0.0)
Requires-Dist: openai (>=1.59.8,<2.0.0)
Requires-Dist: pillow (>=11.1.0,<12.0.0)
Requires-Dist: qwen-vl-utils (>=0.0.8,<0.0.9)
Requires-Dist: requests (>=2.32.3,<3.0.0)
Requires-Dist: torch (==2.3.0)
Requires-Dist: torchvision (==0.18.0)
Requires-Dist: transformers (==4.43.0)
Project-URL: Homepage, https://github.com/yasho191/SwiftAnnotate
Project-URL: Repository, https://github.com/yasho191/SwiftAnnotate
